LuminaScan/__init__.py
LuminaScan/main.py
luminascan-1.0.8.dist-info/licenses/LICENSE
luminascan-1.0.8.dist-info/METADATA
luminascan-1.0.8.dist-info/WHEEL
luminascan-1.0.8.dist-info/entry_points.txt
luminascan-1.0.8.dist-info/top_level.txt
luminascan-1.0.8.dist-info/RECORD
