Metadata-Version: 2.4
Name: LuminaScan
Version: 1.0.8
Summary: Tool to analyze website and APIs via HTTP requests
Home-page: https://github.com/PixelPirate-bit/LuminaScan
Author: PixelPirate-bit-2
License: MIT
Requires-Python: >=3.8
License-File: LICENSE
Requires-Dist: requests>=2.25.1
Requires-Dist: pyfiglet>=0.8.post1
Requires-Dist: colorama>=0.4.4
Dynamic: author
Dynamic: description
Dynamic: description-content-type
Dynamic: home-page
Dynamic: license
Dynamic: license-file
Dynamic: requires-dist
Dynamic: requires-python
Dynamic: summary
